EasyFlow-0.1.dev3.data/scripts/test.py
EasyFlow-0.1.dev3.dist-info/METADATA
EasyFlow-0.1.dev3.dist-info/RECORD
EasyFlow-0.1.dev3.dist-info/WHEEL
EasyFlow-0.1.dev3.dist-info/top_level.txt
easyflow/__init__.py
easyflow/core/__init__.py
easyflow/core/abstract_model.py
easyflow/core/layers/__init__.py
easyflow/core/layers/capsule.py
easyflow/core/layers/simple.py
easyflow/core/layers/variables.py
easyflow/pipeline/__init__.py
easyflow/pipeline/data_extractor.py
easyflow/pipeline/data_feeder.py
easyflow/pipeline/data_reader.py
