Metadata-Version: 2.1
Name: EasyFlow
Version: 0.1.dev3
Summary: Modular Distributed TensorFlow Framework
Home-page: http://pypi.python.org/pypi/EasyFlow/
Author: Rohit Jain
Author-email: rohit06nitbpl@gmail.com
License: LICENSE.txt
Platform: UNKNOWN
